openqasm3/__init__.py
openqasm3/ast.py
openqasm3/parser.py
openqasm3/printer.py
openqasm3/properties.py
openqasm3/py.typed
openqasm3/spec.py
openqasm3/visitor.py
openqasm3/_antlr/__init__.py
openqasm3/_antlr/_4_10/qasm3Lexer.interp
openqasm3/_antlr/_4_10/qasm3Lexer.py
openqasm3/_antlr/_4_10/qasm3Lexer.tokens
openqasm3/_antlr/_4_10/qasm3Parser.interp
openqasm3/_antlr/_4_10/qasm3Parser.py
openqasm3/_antlr/_4_10/qasm3Parser.tokens
openqasm3/_antlr/_4_10/qasm3ParserListener.py
openqasm3/_antlr/_4_10/qasm3ParserVisitor.py
openqasm3/_antlr/_4_11/qasm3Lexer.interp
openqasm3/_antlr/_4_11/qasm3Lexer.py
openqasm3/_antlr/_4_11/qasm3Lexer.tokens
openqasm3/_antlr/_4_11/qasm3Parser.interp
openqasm3/_antlr/_4_11/qasm3Parser.py
openqasm3/_antlr/_4_11/qasm3Parser.tokens
openqasm3/_antlr/_4_11/qasm3ParserListener.py
openqasm3/_antlr/_4_11/qasm3ParserVisitor.py
openqasm3/_antlr/_4_12/qasm3Lexer.interp
openqasm3/_antlr/_4_12/qasm3Lexer.py
openqasm3/_antlr/_4_12/qasm3Lexer.tokens
openqasm3/_antlr/_4_12/qasm3Parser.interp
openqasm3/_antlr/_4_12/qasm3Parser.py
openqasm3/_antlr/_4_12/qasm3Parser.tokens
openqasm3/_antlr/_4_12/qasm3ParserListener.py
openqasm3/_antlr/_4_12/qasm3ParserVisitor.py
openqasm3/_antlr/_4_13/qasm3Lexer.interp
openqasm3/_antlr/_4_13/qasm3Lexer.py
openqasm3/_antlr/_4_13/qasm3Lexer.tokens
openqasm3/_antlr/_4_13/qasm3Parser.interp
openqasm3/_antlr/_4_13/qasm3Parser.py
openqasm3/_antlr/_4_13/qasm3Parser.tokens
openqasm3/_antlr/_4_13/qasm3ParserListener.py
openqasm3/_antlr/_4_13/qasm3ParserVisitor.py
openqasm3/_antlr/_4_7/qasm3Lexer.interp
openqasm3/_antlr/_4_7/qasm3Lexer.py
openqasm3/_antlr/_4_7/qasm3Lexer.tokens
openqasm3/_antlr/_4_7/qasm3Parser.interp
openqasm3/_antlr/_4_7/qasm3Parser.py
openqasm3/_antlr/_4_7/qasm3Parser.tokens
openqasm3/_antlr/_4_7/qasm3ParserListener.py
openqasm3/_antlr/_4_7/qasm3ParserVisitor.py
openqasm3/_antlr/_4_8/qasm3Lexer.interp
openqasm3/_antlr/_4_8/qasm3Lexer.py
openqasm3/_antlr/_4_8/qasm3Lexer.tokens
openqasm3/_antlr/_4_8/qasm3Parser.interp
openqasm3-1.0.0.dist-info/LICENSE.txt
openqasm3-1.0.0.dist-info/METADATA
openqasm3-1.0.0.dist-info/WHEEL
openqasm3-1.0.0.dist-info/top_level.txt
openqasm3-1.0.0.dist-info/RECORD
