Metadata-Version: 2.1
Name: openqasm3
Version: 1.0.0
Summary: Reference OpenQASM AST in Python
Home-page: https://github.com/openqasm/openqasm
Author: OpenQASM Contributors
License: Apache 2.0 Software License
Keywords: openqasm quantum
Classifier: License :: OSI Approved :: Apache Software License
Classifier: Intended Audience :: Developers
Classifier: Intended Audience :: Science/Research
Classifier: Operating System :: Microsoft :: Windows
Classifier: Operating System :: MacOS
Classifier: Operating System :: POSIX :: Linux
Classifier: Programming Language :: Python :: 3 :: Only
Classifier: Topic :: Scientific/Engineering
License-File: LICENSE.txt
Provides-Extra: parser
Requires-Dist: antlr4_python3_runtime<4.14,>=4.7; extra == "parser"
Requires-Dist: importlib_metadata; python_version < "3.10" and extra == "parser"
Provides-Extra: tests
Requires-Dist: pytest>=6.0; extra == "tests"
Requires-Dist: pyyaml; extra == "tests"
Provides-Extra: all
Requires-Dist: antlr4_python3_runtime<4.14,>=4.7; extra == "all"
Requires-Dist: importlib_metadata; python_version < "3.10" and extra == "all"
Requires-Dist: pytest>=6.0; extra == "all"
Requires-Dist: pyyaml; extra == "all"
